{"cameraMode":{"drawMode":0,"name":"Shaded","section":"Shading Mode"},"sceneLighting":true,"audioPlay":false,"sceneViewState":{"m_AlwaysRefresh":false,"showFog":true,"showSkybox":true,"showFlares":true,"showImageEffects":true,"showParticleSystems":true,"showVisualEffectGraphs":true,"m_FxEnabled":true},"in2DMode":false,"pivot":{"x":-3.5491628646850588,"y":4.286759853363037,"z":-8.342586517333985},"rotation":{"x":-0.2968263328075409,"y":0.2611209750175476,"z":-0.08474305272102356,"w":-0.9146225452423096},"size":20.560592651367189,"orthographic":false}